{
  "type": "FeatureCollection",
  "features": [
    {
      "type": "Feature",
      "properties": {
        "name": "Sample Station",
        "line": "Sample Line"
      },
      "geometry": {
        "type": "Point",
        "coordinates": [139.767, 35.681]
      }
    }
  ]
}
